{
  "id": "953e6cf5-114d-4684-aee0-683c8ab2741a",
  "prevId": "77128095-d38d-4ded-b41d-cdde86ab18a0",
  "version": "7",
  "dialect": "postgresql",
  "tables": {
    "public.game_profiles": {
      "name": "game_profiles",
      "schema": "",
      "columns": {
        "id": {
          "name": "id",
          "type": "uuid",
          "primaryKey": true,
          "notNull": true,
          "default": "gen_random_uuid()"
        },
        "user_id": {
          "name": "user_id",
          "type": "uuid",
          "primaryKey": false,
          "notNull": true
        },
        "total_xp": {
          "name": "total_xp",
          "type": "integer",
          "primaryKey": false,
          "notNull": true,
          "default": 0
        },
        "level": {
          "name": "level",
          "type": "integer",
          "primaryKey": false,
          "notNull": true,
          "default": 1
        },
        "current_streak": {
          "name": "current_streak",
          "type": "integer",
          "primaryKey": false,
          "notNull": true,
          "default": 0
        },
        "daily_streak": {
          "name": "daily_streak",
          "type": "integer",
          "primaryKey": false,
          "notNull": true,
          "default": 0
        },
        "last_played_at": {
          "name": "last_played_at",
          "type": "timestamp",
          "primaryKey": false,
          "notNull": false
        },
        "earned_badges": {
          "name": "earned_badges",
          "type": "jsonb",
          "primaryKey": false,
          "notNull": true,
          "default": "'[]'::jsonb"
        }
      },
      "indexes": {},
      "foreignKeys": {
        "game_profiles_user_id_users_id_fk": {
          "name": "game_profiles_user_id_users_id_fk",
          "tableFrom": "game_profiles",
          "tableTo": "users",
          "columnsFrom": [
            "user_id"
          ],
          "columnsTo": [
            "id"
          ],
          "onDelete": "no action",
          "onUpdate": "no action"
        }
      },
      "compositePrimaryKeys": {},
      "uniqueConstraints": {
        "game_profiles_user_id_unique": {
          "name": "game_profiles_user_id_unique",
          "nullsNotDistinct": false,
          "columns": [
            "user_id"
          ]
        }
      },
      "policies": {},
      "checkConstraints": {},
      "isRLSEnabled": false
    },
    "public.progress": {
      "name": "progress",
      "schema": "",
      "columns": {
        "id": {
          "name": "id",
          "type": "uuid",
          "primaryKey": true,
          "notNull": true,
          "default": "gen_random_uuid()"
        },
        "user_id": {
          "name": "user_id",
          "type": "uuid",
          "primaryKey": false,
          "notNull": true
        },
        "word_id": {
          "name": "word_id",
          "type": "uuid",
          "primaryKey": false,
          "notNull": true
        },
        "correct_count": {
          "name": "correct_count",
          "type": "integer",
          "primaryKey": false,
          "notNull": true,
          "default": 0
        },
        "incorrect_count": {
          "name": "incorrect_count",
          "type": "integer",
          "primaryKey": false,
          "notNull": true,
          "default": 0
        },
        "ease_factor": {
          "name": "ease_factor",
          "type": "real",
          "primaryKey": false,
          "notNull": true,
          "default": 2.5
        },
        "interval": {
          "name": "interval",
          "type": "integer",
          "primaryKey": false,
          "notNull": true,
          "default": 0
        },
        "next_review_at": {
          "name": "next_review_at",
          "type": "timestamp",
          "primaryKey": false,
          "notNull": false
        }
      },
      "indexes": {},
      "foreignKeys": {
        "progress_user_id_users_id_fk": {
          "name": "progress_user_id_users_id_fk",
          "tableFrom": "progress",
          "tableTo": "users",
          "columnsFrom": [
            "user_id"
          ],
          "columnsTo": [
            "id"
          ],
          "onDelete": "no action",
          "onUpdate": "no action"
        },
        "progress_word_id_words_id_fk": {
          "name": "progress_word_id_words_id_fk",
          "tableFrom": "progress",
          "tableTo": "words",
          "columnsFrom": [
            "word_id"
          ],
          "columnsTo": [
            "id"
          ],
          "onDelete": "cascade",
          "onUpdate": "no action"
        }
      },
      "compositePrimaryKeys": {},
      "uniqueConstraints": {
        "progress_user_word": {
          "name": "progress_user_word",
          "nullsNotDistinct": false,
          "columns": [
            "user_id",
            "word_id"
          ]
        }
      },
      "policies": {},
      "checkConstraints": {},
      "isRLSEnabled": false
    },
    "public.session_results": {
      "name": "session_results",
      "schema": "",
      "columns": {
        "id": {
          "name": "id",
          "type": "uuid",
          "primaryKey": true,
          "notNull": true,
          "default": "gen_random_uuid()"
        },
        "session_id": {
          "name": "session_id",
          "type": "uuid",
          "primaryKey": false,
          "notNull": true
        },
        "word_id": {
          "name": "word_id",
          "type": "uuid",
          "primaryKey": false,
          "notNull": true
        },
        "exercise_type": {
          "name": "exercise_type",
          "type": "text",
          "primaryKey": false,
          "notNull": true
        },
        "correct": {
          "name": "correct",
          "type": "boolean",
          "primaryKey": false,
          "notNull": true
        },
        "attempt_number": {
          "name": "attempt_number",
          "type": "integer",
          "primaryKey": false,
          "notNull": true
        }
      },
      "indexes": {},
      "foreignKeys": {
        "session_results_session_id_sessions_id_fk": {
          "name": "session_results_session_id_sessions_id_fk",
          "tableFrom": "session_results",
          "tableTo": "sessions",
          "columnsFrom": [
            "session_id"
          ],
          "columnsTo": [
            "id"
          ],
          "onDelete": "cascade",
          "onUpdate": "no action"
        },
        "session_results_word_id_words_id_fk": {
          "name": "session_results_word_id_words_id_fk",
          "tableFrom": "session_results",
          "tableTo": "words",
          "columnsFrom": [
            "word_id"
          ],
          "columnsTo": [
            "id"
          ],
          "onDelete": "cascade",
          "onUpdate": "no action"
        }
      },
      "compositePrimaryKeys": {},
      "uniqueConstraints": {},
      "policies": {},
      "checkConstraints": {},
      "isRLSEnabled": false
    },
    "public.sessions": {
      "name": "sessions",
      "schema": "",
      "columns": {
        "id": {
          "name": "id",
          "type": "uuid",
          "primaryKey": true,
          "notNull": true,
          "default": "gen_random_uuid()"
        },
        "user_id": {
          "name": "user_id",
          "type": "uuid",
          "primaryKey": false,
          "notNull": true
        },
        "word_list_id": {
          "name": "word_list_id",
          "type": "uuid",
          "primaryKey": false,
          "notNull": false
        },
        "started_at": {
          "name": "started_at",
          "type": "timestamp",
          "primaryKey": false,
          "notNull": true,
          "default": "now()"
        },
        "ended_at": {
          "name": "ended_at",
          "type": "timestamp",
          "primaryKey": false,
          "notNull": false
        }
      },
      "indexes": {},
      "foreignKeys": {
        "sessions_user_id_users_id_fk": {
          "name": "sessions_user_id_users_id_fk",
          "tableFrom": "sessions",
          "tableTo": "users",
          "columnsFrom": [
            "user_id"
          ],
          "columnsTo": [
            "id"
          ],
          "onDelete": "no action",
          "onUpdate": "no action"
        },
        "sessions_word_list_id_word_lists_id_fk": {
          "name": "sessions_word_list_id_word_lists_id_fk",
          "tableFrom": "sessions",
          "tableTo": "word_lists",
          "columnsFrom": [
            "word_list_id"
          ],
          "columnsTo": [
            "id"
          ],
          "onDelete": "no action",
          "onUpdate": "no action"
        }
      },
      "compositePrimaryKeys": {},
      "uniqueConstraints": {},
      "policies": {},
      "checkConstraints": {},
      "isRLSEnabled": false
    },
    "public.users": {
      "name": "users",
      "schema": "",
      "columns": {
        "id": {
          "name": "id",
          "type": "uuid",
          "primaryKey": true,
          "notNull": true,
          "default": "gen_random_uuid()"
        },
        "username": {
          "name": "username",
          "type": "text",
          "primaryKey": false,
          "notNull": true
        },
        "password_hash": {
          "name": "password_hash",
          "type": "text",
          "primaryKey": false,
          "notNull": true
        },
        "role": {
          "name": "role",
          "type": "text",
          "primaryKey": false,
          "notNull": true
        },
        "parent_id": {
          "name": "parent_id",
          "type": "uuid",
          "primaryKey": false,
          "notNull": false
        },
        "created_at": {
          "name": "created_at",
          "type": "timestamp",
          "primaryKey": false,
          "notNull": true,
          "default": "now()"
        }
      },
      "indexes": {},
      "foreignKeys": {
        "users_parent_id_users_id_fk": {
          "name": "users_parent_id_users_id_fk",
          "tableFrom": "users",
          "tableTo": "users",
          "columnsFrom": [
            "parent_id"
          ],
          "columnsTo": [
            "id"
          ],
          "onDelete": "no action",
          "onUpdate": "no action"
        }
      },
      "compositePrimaryKeys": {},
      "uniqueConstraints": {
        "users_username_unique": {
          "name": "users_username_unique",
          "nullsNotDistinct": false,
          "columns": [
            "username"
          ]
        }
      },
      "policies": {},
      "checkConstraints": {},
      "isRLSEnabled": false
    },
    "public.word_lists": {
      "name": "word_lists",
      "schema": "",
      "columns": {
        "id": {
          "name": "id",
          "type": "uuid",
          "primaryKey": true,
          "notNull": true,
          "default": "gen_random_uuid()"
        },
        "name": {
          "name": "name",
          "type": "text",
          "primaryKey": false,
          "notNull": true
        },
        "created_by": {
          "name": "created_by",
          "type": "uuid",
          "primaryKey": false,
          "notNull": true
        },
        "is_builtin": {
          "name": "is_builtin",
          "type": "boolean",
          "primaryKey": false,
          "notNull": true,
          "default": false
        },
        "created_at": {
          "name": "created_at",
          "type": "timestamp",
          "primaryKey": false,
          "notNull": true,
          "default": "now()"
        }
      },
      "indexes": {},
      "foreignKeys": {
        "word_lists_created_by_users_id_fk": {
          "name": "word_lists_created_by_users_id_fk",
          "tableFrom": "word_lists",
          "tableTo": "users",
          "columnsFrom": [
            "created_by"
          ],
          "columnsTo": [
            "id"
          ],
          "onDelete": "no action",
          "onUpdate": "no action"
        }
      },
      "compositePrimaryKeys": {},
      "uniqueConstraints": {},
      "policies": {},
      "checkConstraints": {},
      "isRLSEnabled": false
    },
    "public.words": {
      "name": "words",
      "schema": "",
      "columns": {
        "id": {
          "name": "id",
          "type": "uuid",
          "primaryKey": true,
          "notNull": true,
          "default": "gen_random_uuid()"
        },
        "word": {
          "name": "word",
          "type": "text",
          "primaryKey": false,
          "notNull": true
        },
        "word_list_id": {
          "name": "word_list_id",
          "type": "uuid",
          "primaryKey": false,
          "notNull": true
        }
      },
      "indexes": {},
      "foreignKeys": {
        "words_word_list_id_word_lists_id_fk": {
          "name": "words_word_list_id_word_lists_id_fk",
          "tableFrom": "words",
          "tableTo": "word_lists",
          "columnsFrom": [
            "word_list_id"
          ],
          "columnsTo": [
            "id"
          ],
          "onDelete": "cascade",
          "onUpdate": "no action"
        }
      },
      "compositePrimaryKeys": {},
      "uniqueConstraints": {},
      "policies": {},
      "checkConstraints": {},
      "isRLSEnabled": false
    }
  },
  "enums": {},
  "schemas": {},
  "sequences": {},
  "roles": {},
  "policies": {},
  "views": {},
  "_meta": {
    "columns": {},
    "schemas": {},
    "tables": {}
  }
}